[
  {
    "id": "alpha-studio",
    "siteName": "Alpha Studio",
    "domain": "alpha.example.com",
    "logo": "/logos/alpha.svg",
    "themeColor": "#2563eb",
    "title": "Alpha Studio | Practical Growth Systems",
    "description": "Alpha Studio publishes practical playbooks for small teams building better web presence.",
    "keywords": [
      "growth",
      "websites",
      "content",
      "small business"
    ],
    "contactEmail": "hello@alpha.example.com",
    "heroTitle": "Build a sharper web presence in less time",
    "heroSubtitle": "Simple content, clean pages, and repeatable publishing for growing teams.",
    "articles": [
      "launch-checklist",
      "content-calendar",
      "local-seo-basics",
      "conversion-copy",
      "analytics-foundation"
    ]
  },
  {
    "id": "green-market",
    "siteName": "Green Market Guide",
    "domain": "green.example.com",
    "logo": "/logos/green.svg",
    "themeColor": "#16a34a",
    "title": "Green Market Guide | Sustainable Business Notes",
    "description": "Green Market Guide shares clear articles for sustainable shops and local brands.",
    "keywords": [
      "sustainability",
      "local business",
      "retail",
      "marketing"
    ],
    "contactEmail": "team@green.example.com",
    "heroTitle": "Clear guidance for sustainable local brands",
    "heroSubtitle": "A lightweight site template for articles, trust pages, and customer contact.",
    "articles": [
      "sustainable-branding",
      "launch-checklist",
      "local-seo-basics",
      "trust-signals",
      "analytics-foundation"
    ]
  },
  {
    "id": "northline-finance",
    "siteName": "Northline Finance",
    "domain": "northline.example.com",
    "logo": "/logos/northline.svg",
    "themeColor": "#0f766e",
    "title": "Northline Finance | Simple Money Guides for Modern Teams",
    "description": "Northline Finance publishes clear guides about budgeting, planning, and financial operations for lean businesses.",
    "keywords": [
      "finance",
      "budgeting",
      "planning",
      "operations"
    ],
    "contactEmail": "hello@northline.example.com",
    "heroTitle": "Financial clarity for practical operators",
    "heroSubtitle": "Plain-English articles that help small teams plan, measure, and grow with confidence.",
    "articles": [
      "launch-checklist",
      "analytics-foundation",
      "conversion-copy",
      "trust-signals",
      "content-calendar"
    ]
  },
  {
    "id": "pixel-harbor",
    "siteName": "Pixel Harbor",
    "domain": "pixelharbor.example.com",
    "logo": "/logos/pixel-harbor.svg",
    "themeColor": "#db2777",
    "title": "Pixel Harbor | Design Notes for Digital Brands",
    "description": "Pixel Harbor helps creators and service businesses improve websites with thoughtful design and useful content.",
    "keywords": [
      "design",
      "branding",
      "portfolio",
      "creative business"
    ],
    "contactEmail": "studio@pixelharbor.example.com",
    "heroTitle": "Design-led websites for memorable brands",
    "heroSubtitle": "A flexible site sample for studios, portfolios, and creative service teams.",
    "articles": [
      "conversion-copy",
      "content-calendar",
      "launch-checklist",
      "trust-signals",
      "local-seo-basics"
    ]
  },
  {
    "id": "bright-health-lab",
    "siteName": "Bright Health Lab",
    "domain": "brighthealth.example.com",
    "logo": "/logos/bright-health.svg",
    "themeColor": "#ea580c",
    "title": "Bright Health Lab | Wellness Content and Clinic Growth",
    "description": "Bright Health Lab shares approachable website and content ideas for clinics, wellness teams, and health educators.",
    "keywords": [
      "health",
      "wellness",
      "clinic marketing",
      "patient education"
    ],
    "contactEmail": "care@brighthealth.example.com",
    "heroTitle": "Helpful health content that earns trust",
    "heroSubtitle": "Give patients and clients a cleaner path to learn, contact, and take the next step.",
    "articles": [
      "trust-signals",
      "launch-checklist",
      "analytics-foundation",
      "content-calendar",
      "sustainable-branding"
    ]
  },
  {
    "id": "craft-table",
    "siteName": "Craft Table",
    "domain": "crafttable.example.com",
    "logo": "/logos/craft-table.svg",
    "themeColor": "#7c3aed",
    "title": "Craft Table | Restaurant Website Playbooks",
    "description": "Craft Table gives restaurants, cafes, and food makers simple playbooks for stronger local web presence.",
    "keywords": [
      "restaurant",
      "cafe",
      "local SEO",
      "hospitality"
    ],
    "contactEmail": "hello@crafttable.example.com",
    "heroTitle": "A better online table for local food brands",
    "heroSubtitle": "Publish menus, stories, guides, and contact pages without overcomplicating the stack.",
    "articles": [
      "local-seo-basics",
      "trust-signals",
      "launch-checklist",
      "conversion-copy",
      "content-calendar"
    ]
  },
  {
    "id": "atlas-learning",
    "siteName": "Atlas Learning",
    "domain": "atlaslearning.example.com",
    "logo": "/logos/atlas-learning.svg",
    "themeColor": "#0891b2",
    "title": "Atlas Learning | Education Content Sites Made Simple",
    "description": "Atlas Learning provides lightweight content site examples for tutors, course creators, and education teams.",
    "keywords": [
      "education",
      "courses",
      "tutoring",
      "learning"
    ],
    "contactEmail": "team@atlaslearning.example.com",
    "heroTitle": "Organize learning content into useful pages",
    "heroSubtitle": "A clean static site pattern for guides, lessons, articles, and student contact flows.",
    "articles": [
      "content-calendar",
      "analytics-foundation",
      "conversion-copy",
      "launch-checklist",
      "local-seo-basics"
    ]
  },
  {
    "id": "xp786-guide",
    "siteName": "XP786 Guide",
    "domain": "xp786guide.com",
    "logo": "/logos/xp786-guide.svg",
    "themeColor": "#dc2626",
    "title": "XP786 Guide | Practical Online Guides and Updates",
    "description": "XP786 Guide publishes practical articles, launch checklists, and simple website guidance for readers who want clear next steps.",
    "keywords": [
      "XP786 Guide",
      "online guide",
      "website tips",
      "content strategy"
    ],
    "contactEmail": "hello@xp786guide.com",
    "heroTitle": "Clear guides for building a stronger online presence",
    "heroSubtitle": "Read practical articles, planning notes, and launch checklists organized for quick action.",
    "articles": [
      "launch-checklist",
      "content-calendar",
      "local-seo-basics",
      "conversion-copy",
      "trust-signals"
    ]
  },
  {
    "id": "xp786-news",
    "siteName": "XP786 News",
    "domain": "xp786news.example.com",
    "logo": "/logos/xp786-news.svg",
    "themeColor": "#2563eb",
    "title": "XP786 News | Fresh Updates and Practical Online Notes",
    "description": "XP786 News collects timely updates, simple explainers, and practical notes for readers following online trends.",
    "keywords": [
      "XP786 News",
      "online updates",
      "digital news",
      "website guides"
    ],
    "contactEmail": "hello@xp786news.example.com",
    "heroTitle": "Fresh XP786 updates in one simple guide",
    "heroSubtitle": "Follow useful news, launch notes, and practical online tips without digging through noisy sources.",
    "articles": [
      "content-calendar",
      "launch-checklist",
      "analytics-foundation",
      "local-seo-basics",
      "trust-signals"
    ]
  },
  {
    "id": "xp786-hub",
    "siteName": "XP786 Hub",
    "domain": "xp786hub.example.com",
    "logo": "/logos/xp786-hub.svg",
    "themeColor": "#16a34a",
    "title": "XP786 Hub | Resource Center for Online Growth",
    "description": "XP786 Hub provides resource-style articles for planning content, improving web pages, and organizing online growth work.",
    "keywords": [
      "XP786 Hub",
      "resource center",
      "online growth",
      "content planning"
    ],
    "contactEmail": "team@xp786hub.example.com",
    "heroTitle": "A practical hub for online growth resources",
    "heroSubtitle": "Use clear checklists, content ideas, and site improvement guides to move faster.",
    "articles": [
      "local-seo-basics",
      "conversion-copy",
      "content-calendar",
      "analytics-foundation",
      "launch-checklist"
    ]
  },
  {
    "id": "xp786-tips",
    "siteName": "XP786 Tips",
    "domain": "xp786tips.example.com",
    "logo": "/logos/xp786-tips.svg",
    "themeColor": "#f59e0b",
    "title": "XP786 Tips | Simple Website and Content Tips",
    "description": "XP786 Tips publishes short, actionable advice for improving website content, trust signals, and visitor paths.",
    "keywords": [
      "XP786 Tips",
      "website tips",
      "content tips",
      "SEO basics"
    ],
    "contactEmail": "tips@xp786tips.example.com",
    "heroTitle": "Short tips for better online pages",
    "heroSubtitle": "Quick, practical ideas for cleaner pages, stronger content, and easier visitor decisions.",
    "articles": [
      "conversion-copy",
      "trust-signals",
      "local-seo-basics",
      "launch-checklist",
      "content-calendar"
    ]
  },
  {
    "id": "xp786-review",
    "siteName": "XP786 Review",
    "domain": "xp786review.example.com",
    "logo": "/logos/xp786-review.svg",
    "themeColor": "#9333ea",
    "title": "XP786 Review | Guides, Reviews, and Website Checklists",
    "description": "XP786 Review organizes review-style content, trust guidance, and practical website checklists for online readers.",
    "keywords": [
      "XP786 Review",
      "reviews",
      "online checklist",
      "trust signals"
    ],
    "contactEmail": "reviews@xp786review.example.com",
    "heroTitle": "Review-style guides with practical next steps",
    "heroSubtitle": "Compare ideas, check key details, and use simple guides to improve online decisions.",
    "articles": [
      "trust-signals",
      "analytics-foundation",
      "conversion-copy",
      "launch-checklist",
      "local-seo-basics"
    ]
  }
]
